setup.py
mhidayat_dsnd_probability/Binomialdistribution.py
mhidayat_dsnd_probability/Gaussiandistribution.py
mhidayat_dsnd_probability/Generaldistribution.py
mhidayat_dsnd_probability/__init__.py
mhidayat_dsnd_probability.egg-info/PKG-INFO
mhidayat_dsnd_probability.egg-info/SOURCES.txt
mhidayat_dsnd_probability.egg-info/dependency_links.txt
mhidayat_dsnd_probability.egg-info/not-zip-safe
mhidayat_dsnd_probability.egg-info/top_level.txt