Metadata-Version: 1.0
Name: mhidayat-dsnd-probability
Version: 0.1
Summary: Gaussian distributions
Home-page: UNKNOWN
Author: Muhammad Hidayat
Author-email: mhidayatz86@gmail.com
License: UNKNOWN
Platform: UNKNOWN
